manggee_cmd/__init__.py
manggee_cmd/cmd.py
manggee_cmd-0.1.0.dist-info/METADATA
manggee_cmd-0.1.0.dist-info/WHEEL
manggee_cmd-0.1.0.dist-info/entry_points.txt
manggee_cmd-0.1.0.dist-info/top_level.txt
manggee_cmd-0.1.0.dist-info/RECORD
