Metadata-Version: 2.1
Name: manggee_cmd
Version: 0.1.0
Summary: Default template for PDM package
Author-email: mangG907 <mang.gee@gmail.com>
License: MIT
Requires-Python: >=3.9
